cortex_memory/__init__.py
cortex_memory/cli.py
cortex_memory/client.py
cortex_memory/config.py
cortex_memory/context_manager.py
cortex_memory/core.py
cortex_memory/gemini_api.py
cortex_memory/llm_providers.py
cortex_memory/redis_client.py
cortex_memory/self_evolving_context.py
cortex_memory/semantic_drift_detection.py
cortex_memory/semantic_embeddings.py
cortex_memory_sdk-2.0.3.dist-info/METADATA
cortex_memory_sdk-2.0.3.dist-info/WHEEL
cortex_memory_sdk-2.0.3.dist-info/entry_points.txt
cortex_memory_sdk-2.0.3.dist-info/top_level.txt
cortex_memory_sdk-2.0.3.dist-info/RECORD
